deltachat_rpc_client/__init__.py
deltachat_rpc_client/_utils.py
deltachat_rpc_client/account.py
deltachat_rpc_client/chat.py
deltachat_rpc_client/client.py
deltachat_rpc_client/const.py
deltachat_rpc_client/contact.py
deltachat_rpc_client/deltachat.py
deltachat_rpc_client/events.py
deltachat_rpc_client/message.py
deltachat_rpc_client/py.typed
deltachat_rpc_client/pytestplugin.py
deltachat_rpc_client/rpc.py
deltachat_rpc_client-2.39.0.dist-info/licenses/LICENSE
deltachat_rpc_client-2.39.0.dist-info/METADATA
deltachat_rpc_client-2.39.0.dist-info/WHEEL
deltachat_rpc_client-2.39.0.dist-info/entry_points.txt
deltachat_rpc_client-2.39.0.dist-info/top_level.txt
deltachat_rpc_client-2.39.0.dist-info/RECORD
