Metadata-Version: 2.4
Name: deltachat-rpc-client
Version: 2.39.0
Summary: Python client for Delta Chat core JSON-RPC interface
License-Expression: MPL-2.0
Classifier: Development Status :: 5 - Production/Stable
Classifier: Intended Audience :: Developers
Classifier: Operating System :: POSIX :: Linux
Classifier: Operating System :: MacOS :: MacOS X
Classifier: Programming Language :: Python :: 3
Classifier: Programming Language :: Python :: 3.10
Classifier: Programming Language :: Python :: 3.11
Classifier: Programming Language :: Python :: 3.12
Classifier: Programming Language :: Python :: 3.13
Classifier: Programming Language :: Python :: 3.14
Classifier: Topic :: Communications :: Chat
Classifier: Topic :: Communications :: Email
Requires-Python: >=3.10
License-File: LICENSE
Dynamic: license-file
